oraculo/__init__.py
oraculo/cli.py
oraculo/functions/__init__.py
oraculo/functions/audio.py
oraculo/functions/config.py
oraculo/functions/data.py
oraculo/webapp/__init__.py
oraculo/webapp/hello_world.py
oraculo/webapp/pages/add_document.py
oraculo-0.1.14.dist-info/METADATA
oraculo-0.1.14.dist-info/WHEEL
oraculo-0.1.14.dist-info/entry_points.txt
oraculo-0.1.14.dist-info/RECORD
